chemner/__init__.py
chemner/package_data.dat
chemner/simple.py
chemner-0.0.2.data/data/chemmorpheme/chemmorpheme.dat
chemner-0.0.2.data/data/chemtagged/chemtagged.dat
chemner-0.0.2.data/data/testset/testset.txt
sample/__init__.py
sample/package_data.dat
sample/simple.py
chemner-0.0.2.dist-info/LICENSE
chemner-0.0.2.dist-info/METADATA
chemner-0.0.2.dist-info/WHEEL
chemner-0.0.2.dist-info/entry_points.txt
chemner-0.0.2.dist-info/top_level.txt
chemner-0.0.2.dist-info/RECORD
