Metadata-Version: 2.1
Name: chemner
Version: 0.0.2
Summary: Chinese Chemical Named Entity Recognition
Home-page: https://github.com/xiabo0816/chemner
Author: A. BLCU
Author-email: blcuxiabo@126.com
License: UNKNOWN
Project-URL: Bug Reports, https://github.com/xiabo0816/chemner/issues
Project-URL: Funding, https://donate.pypi.org
Project-URL: Say Thanks!, https://github.com/xiabo0816/chemner/
Project-URL: Source, https://github.com/xiabo0816/chemner/
Keywords: chemner,setuptools,development
Platform: UNKNOWN
Classifier: Development Status :: 3 - Alpha
Classifier: Intended Audience :: Developers
Classifier: Topic :: Software Development :: Build Tools
Classifier: License :: OSI Approved :: MIT License
Classifier: Programming Language :: Python :: 3
Classifier: Programming Language :: Python :: 3.5
Classifier: Programming Language :: Python :: 3.6
Classifier: Programming Language :: Python :: 3.7
Classifier: Programming Language :: Python :: 3.8
Classifier: Programming Language :: Python :: 3.9
Classifier: Programming Language :: Python :: 3 :: Only
Requires-Python: >=3.5, <4
Requires-Dist: peppercorn
Provides-Extra: dev
Requires-Dist: check-manifest ; extra == 'dev'
Provides-Extra: test
Requires-Dist: coverage ; extra == 'test'
